ofxstatement_satispay/__init__.py
ofxstatement_satispay/plugin.py
ofxstatement_satispay/utils.py
ofxstatement_satispay-0.2.2.dist-info/METADATA
ofxstatement_satispay-0.2.2.dist-info/WHEEL
ofxstatement_satispay-0.2.2.dist-info/entry_points.txt
ofxstatement_satispay-0.2.2.dist-info/RECORD
